sane_python/__init__.py
sane_python/io.py
sane_python-0.1.2.dist-info/entry_points.txt
sane_python-0.1.2.dist-info/LICENSE
sane_python-0.1.2.dist-info/WHEEL
sane_python-0.1.2.dist-info/METADATA
sane_python-0.1.2.dist-info/RECORD
